{
  "packet_id": "predictive-history-kumhsfxnr5i-semantics-pkt-0007",
  "source_id": "video:predictive-history-kumhsfxnr5i",
  "source_date": "2024-12-19",
  "interactions": [
    {
      "refs": [
        "video:predictive-history-kumhsfxnr5i@transcript:v1#seg-0049"
      ],
      "kind": "answer",
      "summary": "Jiang postpones a student's Islam question and answers a question about authorship of Acts: he says Acts was written by the same writer as Luke, likely 80-90 CE.",
      "speaker_attribution": "Jiang answering audience questions",
      "confidence": "high"
    },
    {
      "refs": [
        "video:predictive-history-kumhsfxnr5i@transcript:v1#seg-0050",
        "video:predictive-history-kumhsfxnr5i@transcript:v1#seg-0051"
      ],
      "kind": "answer",
      "summary": "He explains Acts as a pro-Paul apology written in a context where Paul was hated as a corrupter of Jesus' teaching and suspected of collaboration with Rome, then closes by previewing monotheism as a radical reconception of reality.",
      "speaker_attribution": "Jiang answering audience question and closing lecture",
      "confidence": "high"
    }
  ],
  "speaker_notes": [
    {
      "refs": [
        "video:predictive-history-kumhsfxnr5i@transcript:v1#seg-0049"
      ],
      "note": "The question about Acts is paraphrased by Jiang inside his answer; the student's exact wording is not preserved in the focus refs.",
      "suggested_speaker": "Jiang",
      "confidence": "high"
    }
  ],
  "claims": [
    {
      "claim": "Jiang says the authorship of Acts is unknown, but Acts was written by the same person who wrote Luke.",
      "refs": [
        "video:predictive-history-kumhsfxnr5i@transcript:v1#seg-0049"
      ],
      "temporal_scope": "Lecture Q&A claim on 2024-12-19.",
      "topic_tags": [
        "Acts",
        "Luke",
        "authorship"
      ],
      "claim_type": "evidence",
      "confidence": "high"
    },
    {
      "claim": "Jiang dates Luke to roughly 80-90 CE, about 50-60 years after Jesus' death, and says Paul might still have been alive then.",
      "refs": [
        "video:predictive-history-kumhsfxnr5i@transcript:v1#seg-0049",
        "video:predictive-history-kumhsfxnr5i@transcript:v1#seg-0050"
      ],
      "temporal_scope": "Historical dating claim presented on 2024-12-19.",
      "topic_tags": [
        "Luke",
        "Acts",
        "chronology"
      ],
      "claim_type": "evidence",
      "confidence": "medium"
    },
    {
      "claim": "Acts is very pro-Paul and should be read as a story by people trying to clean up Paul's image.",
      "refs": [
        "video:predictive-history-kumhsfxnr5i@transcript:v1#seg-0050",
        "video:predictive-history-kumhsfxnr5i@transcript:v1#seg-0051"
      ],
      "temporal_scope": "Lecture interpretation on 2024-12-19.",
      "topic_tags": [
        "Acts",
        "Paul",
        "apology"
      ],
      "claim_type": "diagnosis",
      "confidence": "high"
    },
    {
      "claim": "At the time Acts is written, Jiang says many people, especially Jews, hate Paul because they see him as corrupting their religion and Jesus' teachings.",
      "refs": [
        "video:predictive-history-kumhsfxnr5i@transcript:v1#seg-0050"
      ],
      "temporal_scope": "Historical interpretation presented on 2024-12-19.",
      "topic_tags": [
        "Paul",
        "Jewish opposition",
        "corruption"
      ],
      "claim_type": "diagnosis",
      "confidence": "high"
    },
    {
      "claim": "Jiang previews the next lecture's claim that monotheism is not merely belief in one God but a radical reconception of reality.",
      "refs": [
        "video:predictive-history-kumhsfxnr5i@transcript:v1#seg-0051"
      ],
      "temporal_scope": "Forward-looking lecture preview on 2024-12-19.",
      "topic_tags": [
        "monotheism",
        "next lecture",
        "reality"
      ],
      "claim_type": "prediction",
      "confidence": "high"
    }
  ],
  "signature_moments": [
    {
      "refs": [
        "video:predictive-history-kumhsfxnr5i@transcript:v1#seg-0050"
      ],
      "moment": "Acts is not neutral biography; it is a pro-Paul cleanup operation.",
      "source_phrase": "trying to promote a positive picture of Paul",
      "why_it_matters": "It confirms the lecture's method: the canonical text is read as apologetic evidence for the very suspicion it tries to resolve.",
      "tone": "method",
      "confidence": "high"
    },
    {
      "refs": [
        "video:predictive-history-kumhsfxnr5i@transcript:v1#seg-0051"
      ],
      "moment": "Monotheism will be treated as a radical reconception of reality, not just belief in one God.",
      "source_phrase": "a radical reconception of reality",
      "why_it_matters": "It links this Paul episode to the next civilization lecture's broader lens on religion and reality.",
      "tone": "definition",
      "confidence": "high"
    }
  ],
  "glossary_terms": [
    {
      "term": "Acts as apology",
      "refs": [
        "video:predictive-history-kumhsfxnr5i@transcript:v1#seg-0050",
        "video:predictive-history-kumhsfxnr5i@transcript:v1#seg-0051"
      ],
      "definition_or_usage": "Jiang's reading of Acts as a pro-Paul text meant to apologize for or clean up Paul's image.",
      "confidence": "high"
    },
    {
      "term": "monotheism as reality shift",
      "refs": [
        "video:predictive-history-kumhsfxnr5i@transcript:v1#seg-0051"
      ],
      "definition_or_usage": "The previewed claim that monotheism is a reconception of reality rather than merely counting gods.",
      "confidence": "high"
    }
  ],
  "chronology_notes": [
    {
      "refs": [
        "video:predictive-history-kumhsfxnr5i@transcript:v1#seg-0049",
        "video:predictive-history-kumhsfxnr5i@transcript:v1#seg-0051"
      ],
      "note": "This Q&A dates Jiang's Acts/Luke authorship claim and previews the next class on monotheism from the 2024-12-19 lecture.",
      "possible_update_to_prior_position": false,
      "confidence": "high"
    }
  ],
  "uncertainty_notes": [
    {
      "refs": [
        "video:predictive-history-kumhsfxnr5i@transcript:v1#seg-0049"
      ],
      "note": "The start of the segment is boundary-damaged from a student Islam question; the public question should be reconstructed only as far as Jiang explicitly restates it."
    }
  ]
}
