{
  "packet_id": "predictive-history-ra2v9hkahz8-semantics-pkt-0003",
  "source_id": "video:predictive-history-ra2v9hkahz8",
  "source_date": "2025-06-04",
  "interactions": [
    {
      "refs": [
        "video:predictive-history-ra2v9hkahz8@transcript:v1#seg-0017",
        "video:predictive-history-ra2v9hkahz8@transcript:v1#seg-0018"
      ],
      "kind": "monologue",
      "summary": "Jiang states the lecture's three questions: where Freud's Oedipal theory came from, why Freud was secretive, and why Freud and Jung spread so quickly through modernism, which he defines as the cult of the self.",
      "speaker_attribution": "Jiang.",
      "confidence": "high"
    },
    {
      "refs": [
        "video:predictive-history-ra2v9hkahz8@transcript:v1#seg-0019",
        "video:predictive-history-ra2v9hkahz8@transcript:v1#seg-0020",
        "video:predictive-history-ra2v9hkahz8@transcript:v1#seg-0021"
      ],
      "kind": "monologue",
      "summary": "He places Freud in late nineteenth-century Vienna, where urban modernity replaces emotional village life with money, clock time, rational abstraction, and new disciplines of sociology and psychology.",
      "speaker_attribution": "Jiang.",
      "confidence": "high"
    },
    {
      "refs": [
        "video:predictive-history-ra2v9hkahz8@transcript:v1#seg-0022",
        "video:predictive-history-ra2v9hkahz8@transcript:v1#seg-0023",
        "video:predictive-history-ra2v9hkahz8@transcript:v1#seg-0024"
      ],
      "kind": "monologue",
      "summary": "Jiang explains anomie, alienation, and disenchantment as city pathologies, then introduces Freud's early hysterical patients as women whose trauma accounts made him initially advocate for them.",
      "speaker_attribution": "Jiang.",
      "confidence": "high"
    }
  ],
  "speaker_notes": [],
  "claims": [
    {
      "claim": "Modernism is defined as the cult of the self: a culture obsessed with self-improvement and self-empowerment.",
      "refs": [
        "video:predictive-history-ra2v9hkahz8@transcript:v1#seg-0017"
      ],
      "temporal_scope": "Definition used in this lecture.",
      "topic_tags": [
        "modernism",
        "cult-of-the-self",
        "self-improvement"
      ],
      "claim_type": "definition",
      "confidence": "high"
    },
    {
      "claim": "Jiang's thesis is that Freud became famous not because psychoanalysis helped patients, but because it protected powerful men.",
      "refs": [
        "video:predictive-history-ra2v9hkahz8@transcript:v1#seg-0018"
      ],
      "temporal_scope": "Lecture argument as of 2025-06-04.",
      "topic_tags": [
        "Freud",
        "psychoanalysis",
        "power",
        "modernism"
      ],
      "claim_type": "diagnosis",
      "confidence": "high"
    },
    {
      "claim": "Freud's system is presented as godless: sexual urges underpin identity and civilization, religion manages guilt, and truth lies in suppressed memories.",
      "refs": [
        "video:predictive-history-ra2v9hkahz8@transcript:v1#seg-0018",
        "video:predictive-history-ra2v9hkahz8@transcript:v1#seg-0019"
      ],
      "temporal_scope": "Lecture reconstruction of Freud.",
      "topic_tags": [
        "Freud",
        "sexual-urges",
        "religion",
        "suppressed-memory"
      ],
      "claim_type": "model",
      "confidence": "high"
    },
    {
      "claim": "Urban modernity replaces emotionally embedded village life with money, clock time, abstraction, and institutional regulation.",
      "refs": [
        "video:predictive-history-ra2v9hkahz8@transcript:v1#seg-0019",
        "video:predictive-history-ra2v9hkahz8@transcript:v1#seg-0021"
      ],
      "temporal_scope": "Historical diagnosis of Freud's context.",
      "topic_tags": [
        "urban-modernity",
        "Vienna",
        "clock-time",
        "money",
        "abstraction"
      ],
      "claim_type": "diagnosis",
      "confidence": "high"
    },
    {
      "claim": "The move from village to city to internet increases abstraction and produces psychological problems.",
      "refs": [
        "video:predictive-history-ra2v9hkahz8@transcript:v1#seg-0021",
        "video:predictive-history-ra2v9hkahz8@transcript:v1#seg-0022"
      ],
      "temporal_scope": "Lecture model connecting nineteenth-century city life to the present.",
      "topic_tags": [
        "abstraction",
        "city",
        "internet",
        "psychology"
      ],
      "claim_type": "model",
      "confidence": "high"
    },
    {
      "claim": "Freud's early patients are described as traumatized women whose symptoms followed abuse, and early Freud initially believed and advocated for them.",
      "refs": [
        "video:predictive-history-ra2v9hkahz8@transcript:v1#seg-0023",
        "video:predictive-history-ra2v9hkahz8@transcript:v1#seg-0024"
      ],
      "temporal_scope": "Lecture reconstruction of early Freud.",
      "topic_tags": [
        "Freud",
        "hysteria",
        "trauma",
        "patients"
      ],
      "claim_type": "diagnosis",
      "confidence": "high"
    }
  ],
  "signature_moments": [
    {
      "refs": [
        "video:predictive-history-ra2v9hkahz8@transcript:v1#seg-0017"
      ],
      "moment": "Modernism is not first a style; it is the cult of the self.",
      "source_phrase": "the easiest definition is cult of the self",
      "why_it_matters": "This phrase becomes the episode's central shorthand for Freud, Jung, modern art, social media, and depression.",
      "tone": "definition",
      "confidence": "high"
    },
    {
      "refs": [
        "video:predictive-history-ra2v9hkahz8@transcript:v1#seg-0018"
      ],
      "moment": "The lecture's accusation is blunt: psychoanalysis was designed to protect powerful men.",
      "source_phrase": "designed to protect the interests of powerful interests powerful men",
      "why_it_matters": "It gives the Freud story moral stakes beyond intellectual history.",
      "tone": "provocation",
      "confidence": "high"
    },
    {
      "refs": [
        "video:predictive-history-ra2v9hkahz8@transcript:v1#seg-0021"
      ],
      "moment": "The city turns food into abstraction; the internet intensifies that abstraction again.",
      "source_phrase": "from the village to the city, now to the internet",
      "why_it_matters": "It connects Simmel's metropolis to contemporary online life through a concrete everyday image.",
      "tone": "metaphor",
      "confidence": "high"
    }
  ],
  "glossary_terms": [
    {
      "term": "cult of the self",
      "refs": [
        "video:predictive-history-ra2v9hkahz8@transcript:v1#seg-0017"
      ],
      "definition_or_usage": "Jiang's compact definition of modernism as obsession with self-improvement, self-empowerment, and the self as the center of culture.",
      "confidence": "high"
    },
    {
      "term": "anomie",
      "refs": [
        "video:predictive-history-ra2v9hkahz8@transcript:v1#seg-0022"
      ],
      "definition_or_usage": "A city condition where older rules no longer apply and people do not know what to do.",
      "confidence": "medium"
    },
    {
      "term": "alienation",
      "refs": [
        "video:predictive-history-ra2v9hkahz8@transcript:v1#seg-0022",
        "video:predictive-history-ra2v9hkahz8@transcript:v1#seg-0023"
      ],
      "definition_or_usage": "Lack of freedom under regulated, repetitive city life.",
      "confidence": "high"
    },
    {
      "term": "disenchantment",
      "refs": [
        "video:predictive-history-ra2v9hkahz8@transcript:v1#seg-0023"
      ],
      "definition_or_usage": "Feeling like a machine and losing human agency under modern conditions.",
      "confidence": "high"
    }
  ],
  "chronology_notes": [
    {
      "refs": [
        "video:predictive-history-ra2v9hkahz8@transcript:v1#seg-0019",
        "video:predictive-history-ra2v9hkahz8@transcript:v1#seg-0023"
      ],
      "note": "Freud is placed in late nineteenth-century Vienna during the transition from pre-modern village life to modern urban society.",
      "possible_update_to_prior_position": false,
      "confidence": "high"
    }
  ],
  "uncertainty_notes": [
    {
      "refs": [
        "video:predictive-history-ra2v9hkahz8@transcript:v1#seg-0022"
      ],
      "note": "The transcript says enemy, but the context indicates the sociological term anomie."
    }
  ]
}
