{
  "packet_id": "predictive-history-tcxloijz8v0-semantics-pkt-0006",
  "source_id": "video:predictive-history-tcxloijz8v0",
  "source_date": "2025-03-27",
  "interactions": [
    {
      "refs": [
        "video:predictive-history-tcxloijz8v0@transcript:v1#seg-0041",
        "video:predictive-history-tcxloijz8v0@transcript:v1#seg-0042",
        "video:predictive-history-tcxloijz8v0@transcript:v1#seg-0043"
      ],
      "kind": "monologue",
      "summary": "Jiang summarizes the material evidence and introduces John Wesley, Weber, Durkheim, and Simmel as witnesses writing around 1900 when Protestant capitalism was triumphant.",
      "speaker_attribution": "Jiang classroom lecture.",
      "confidence": "high"
    },
    {
      "refs": [
        "video:predictive-history-tcxloijz8v0@transcript:v1#seg-0044",
        "video:predictive-history-tcxloijz8v0@transcript:v1#seg-0045",
        "video:predictive-history-tcxloijz8v0@transcript:v1#seg-0046",
        "video:predictive-history-tcxloijz8v0@transcript:v1#seg-0047",
        "video:predictive-history-tcxloijz8v0@transcript:v1#seg-0048"
      ],
      "kind": "monologue",
      "summary": "He reads and interprets Weber: predestination demands certainty of election, worldly activity disperses doubt, and asceticism legalizes acquisition while condemning enjoyment.",
      "speaker_attribution": "Jiang classroom lecture.",
      "confidence": "high"
    }
  ],
  "speaker_notes": [],
  "claims": [
    {
      "claim": "Banknotes represent the abstraction of wealth: because money is no longer limited by gold, wealth can theoretically become infinite.",
      "refs": [
        "video:predictive-history-tcxloijz8v0@transcript:v1#seg-0041"
      ],
      "temporal_scope": "Lecture claim dated 2025-03-27.",
      "topic_tags": [
        "banknotes",
        "abstract-wealth",
        "infinite-wealth"
      ],
      "claim_type": "definition",
      "confidence": "high"
    },
    {
      "claim": "John Wesley summarizes Protestant economic ethics as gaining all one can, saving all one can, and thereby growing rich as a calling.",
      "refs": [
        "video:predictive-history-tcxloijz8v0@transcript:v1#seg-0042"
      ],
      "temporal_scope": "Lecture claim dated 2025-03-27.",
      "topic_tags": [
        "John-Wesley",
        "Protestant-ethic",
        "frugality"
      ],
      "claim_type": "evidence",
      "confidence": "high"
    },
    {
      "claim": "Around 1900, Jiang says Protestant capitalism had conquered the world through Germany, Britain, and the United States, making Weber, Durkheim, and Simmel diagnose its consequences from inside its triumph.",
      "refs": [
        "video:predictive-history-tcxloijz8v0@transcript:v1#seg-0042",
        "video:predictive-history-tcxloijz8v0@transcript:v1#seg-0043"
      ],
      "temporal_scope": "Lecture claim dated 2025-03-27.",
      "topic_tags": [
        "1900",
        "Protestant-capitalism",
        "sociology"
      ],
      "claim_type": "diagnosis",
      "confidence": "high"
    },
    {
      "claim": "Weber's account says predestination creates a duty to consider oneself chosen, because doubt signals insufficient faith and imperfect grace.",
      "refs": [
        "video:predictive-history-tcxloijz8v0@transcript:v1#seg-0044",
        "video:predictive-history-tcxloijz8v0@transcript:v1#seg-0045"
      ],
      "temporal_scope": "Lecture claim dated 2025-03-27.",
      "topic_tags": [
        "Weber",
        "predestination",
        "self-confidence"
      ],
      "claim_type": "model",
      "confidence": "high"
    },
    {
      "claim": "Worldly activity becomes the means to disperse religious doubt and gain certainty of grace, turning anxiety into work.",
      "refs": [
        "video:predictive-history-tcxloijz8v0@transcript:v1#seg-0045",
        "video:predictive-history-tcxloijz8v0@transcript:v1#seg-0046"
      ],
      "temporal_scope": "Lecture claim dated 2025-03-27.",
      "topic_tags": [
        "work",
        "grace",
        "anxiety"
      ],
      "claim_type": "model",
      "confidence": "high"
    },
    {
      "claim": "Protestant asceticism restricts consumption while freeing acquisition, so unspent surplus wealth moves into banks and imperial state power.",
      "refs": [
        "video:predictive-history-tcxloijz8v0@transcript:v1#seg-0046",
        "video:predictive-history-tcxloijz8v0@transcript:v1#seg-0047"
      ],
      "temporal_scope": "Lecture claim dated 2025-03-27.",
      "topic_tags": [
        "asceticism",
        "banks",
        "empire"
      ],
      "claim_type": "model",
      "confidence": "high"
    },
    {
      "claim": "Jiang argues Protestant capitalism reverses older morality: historically excess wealth meant selfishness, but now excess wealth means divine favor.",
      "refs": [
        "video:predictive-history-tcxloijz8v0@transcript:v1#seg-0047",
        "video:predictive-history-tcxloijz8v0@transcript:v1#seg-0048"
      ],
      "temporal_scope": "Lecture claim dated 2025-03-27.",
      "topic_tags": [
        "wealth",
        "morality",
        "reversal"
      ],
      "claim_type": "diagnosis",
      "confidence": "high"
    }
  ],
  "signature_moments": [
    {
      "refs": [
        "video:predictive-history-tcxloijz8v0@transcript:v1#seg-0042",
        "video:predictive-history-tcxloijz8v0@transcript:v1#seg-0043"
      ],
      "moment": "The year 1900 is staged as capitalism's coronation: Protestant empires think industrial capitalism is divinely sent, while sociologists look for the hidden damage.",
      "source_phrase": "Protestantism, Industrial Revolution, capitalism are all divinely sent by God",
      "why_it_matters": "This is the moment the lecture turns from origin story to judgment.",
      "tone": "reversal",
      "confidence": "high"
    },
    {
      "refs": [
        "video:predictive-history-tcxloijz8v0@transcript:v1#seg-0045",
        "video:predictive-history-tcxloijz8v0@transcript:v1#seg-0046"
      ],
      "moment": "Anxiety is answered by the imperative: work, work, work.",
      "source_phrase": "You have anxiety? How do you deal with anxiety? Work, work, work.",
      "why_it_matters": "It condenses Weber's theology into the rhythm of compulsion.",
      "tone": "causal-chain",
      "confidence": "high"
    },
    {
      "refs": [
        "video:predictive-history-tcxloijz8v0@transcript:v1#seg-0047",
        "video:predictive-history-tcxloijz8v0@transcript:v1#seg-0048"
      ],
      "moment": "Wealth flips from social shame to sacred proof.",
      "source_phrase": "Historically, we believed that those who have too much money are evil. Now we believe that those who have too much money are inherently good.",
      "why_it_matters": "This is one of the lecture's cleanest civilizational reversals.",
      "tone": "reversal",
      "confidence": "high"
    }
  ],
  "glossary_terms": [
    {
      "term": "Protestant ethic",
      "refs": [
        "video:predictive-history-tcxloijz8v0@transcript:v1#seg-0042",
        "video:predictive-history-tcxloijz8v0@transcript:v1#seg-0043",
        "video:predictive-history-tcxloijz8v0@transcript:v1#seg-0044",
        "video:predictive-history-tcxloijz8v0@transcript:v1#seg-0045",
        "video:predictive-history-tcxloijz8v0@transcript:v1#seg-0046"
      ],
      "definition_or_usage": "Work hard, save money, and read worldly success as evidence of divine favor.",
      "confidence": "high"
    },
    {
      "term": "asceticism",
      "refs": [
        "video:predictive-history-tcxloijz8v0@transcript:v1#seg-0046",
        "video:predictive-history-tcxloijz8v0@transcript:v1#seg-0047",
        "video:predictive-history-tcxloijz8v0@transcript:v1#seg-0048"
      ],
      "definition_or_usage": "Self-denial that refuses luxury and channels earnings into accumulation rather than enjoyment.",
      "confidence": "high"
    },
    {
      "term": "certainty of grace",
      "refs": [
        "video:predictive-history-tcxloijz8v0@transcript:v1#seg-0044",
        "video:predictive-history-tcxloijz8v0@transcript:v1#seg-0045",
        "video:predictive-history-tcxloijz8v0@transcript:v1#seg-0046"
      ],
      "definition_or_usage": "The subjective assurance that one belongs to the elect, pursued through intense worldly activity.",
      "confidence": "high"
    }
  ],
  "chronology_notes": [
    {
      "refs": [
        "video:predictive-history-tcxloijz8v0@transcript:v1#seg-0042",
        "video:predictive-history-tcxloijz8v0@transcript:v1#seg-0043"
      ],
      "note": "Jiang identifies circa 1900, before World War I, as the moment Protestant capitalism looked most triumphant and sociologists diagnosed its costs.",
      "possible_update_to_prior_position": false,
      "confidence": "high"
    }
  ],
  "uncertainty_notes": []
}
