{
  "packet_id": "interview-n44of1y7zgo-semantics-pkt-0014",
  "source_id": "video:interview-n44of1y7zgo",
  "source_date": "2026-04-13",
  "interactions": [
    {
      "refs": [
        "video:interview-n44of1y7zgo@transcript:v1#seg-0105",
        "video:interview-n44of1y7zgo@transcript:v1#seg-0106"
      ],
      "kind": "answer",
      "summary": "Jiang agrees with Dugin's critique but says the system is attractive to many people because materialist societies such as China have gained happiness, prosperity, technology, wealth, and space travel; the real question is how many choose resistance.",
      "speaker_attribution": "Jiang",
      "confidence": "high"
    },
    {
      "refs": [
        "video:interview-n44of1y7zgo@transcript:v1#seg-0107",
        "video:interview-n44of1y7zgo@transcript:v1#seg-0108"
      ],
      "kind": "question",
      "summary": "The host connects Jiang's point to despair, algorithmic flooding, Lebanon, Gaza, Epstein becoming a meme, jobs, debt, and exhaustion, asking how people preserve humanity.",
      "speaker_attribution": "Sneako",
      "confidence": "high"
    },
    {
      "refs": [
        "video:interview-n44of1y7zgo@transcript:v1#seg-0109"
      ],
      "kind": "answer",
      "summary": "Jiang says debates like this are key because transnational conversations are better than dismissing participants as CCP or KGB spies.",
      "speaker_attribution": "Jiang",
      "confidence": "high"
    },
    {
      "refs": [
        "video:interview-n44of1y7zgo@transcript:v1#seg-0110",
        "video:interview-n44of1y7zgo@transcript:v1#seg-0111",
        "video:interview-n44of1y7zgo@transcript:v1#seg-0112"
      ],
      "kind": "exchange",
      "summary": "The host closes the panel, then Dugin responds to Jiang by saying material prosperity tempts many Russians and Chinese too, but history may still be moved by a catechonic function beyond popular understanding.",
      "speaker_attribution": "Sneako then Dugin",
      "confidence": "high"
    }
  ],
  "speaker_notes": [
    {
      "refs": [
        "video:interview-n44of1y7zgo@transcript:v1#seg-0105"
      ],
      "note": "Diarization labels are not reliable in this multi-speaker interview; speaker attribution is inferred from conversational role and named address.",
      "suggested_speaker": null,
      "confidence": "medium"
    }
  ],
  "claims": [
    {
      "claim": "Jiang's main difference with Dugin is that the anti-human system remains extremely attractive and people may fight to preserve it because it brought prosperity and happiness.",
      "refs": [
        "video:interview-n44of1y7zgo@transcript:v1#seg-0105"
      ],
      "temporal_scope": "Claim made in this April 13, 2026 interview.",
      "topic_tags": [
        "materialism",
        "china",
        "prosperity",
        "antichrist"
      ],
      "claim_type": "diagnosis",
      "confidence": "high"
    },
    {
      "claim": "Jiang says the crucial question is how many people will choose to resist when the system is attractive.",
      "refs": [
        "video:interview-n44of1y7zgo@transcript:v1#seg-0105",
        "video:interview-n44of1y7zgo@transcript:v1#seg-0106"
      ],
      "temporal_scope": "Claim made in this April 13, 2026 interview.",
      "topic_tags": [
        "resistance",
        "free-will",
        "materialism"
      ],
      "claim_type": "question",
      "confidence": "high"
    },
    {
      "claim": "The host describes algorithmic information flooding as a strategy that exhausts people until Gaza, Lebanon, Epstein, debt, and work all compete for limited care.",
      "refs": [
        "video:interview-n44of1y7zgo@transcript:v1#seg-0107",
        "video:interview-n44of1y7zgo@transcript:v1#seg-0108"
      ],
      "temporal_scope": "Claim made in this April 13, 2026 interview.",
      "topic_tags": [
        "attention-flooding",
        "despair",
        "algorithm"
      ],
      "claim_type": "diagnosis",
      "confidence": "high"
    },
    {
      "claim": "Jiang says international conversations are necessary to escape name-calling frames like CCP spy or KGB spy.",
      "refs": [
        "video:interview-n44of1y7zgo@transcript:v1#seg-0109"
      ],
      "temporal_scope": "Claim made in this April 13, 2026 interview.",
      "topic_tags": [
        "dialogue",
        "transnational-conversation",
        "name-calling"
      ],
      "claim_type": "normative",
      "confidence": "high"
    },
    {
      "claim": "Dugin responds that materialist temptation exists in Russia and China too, but catechonic history may move through a small minority rather than mass understanding.",
      "refs": [
        "video:interview-n44of1y7zgo@transcript:v1#seg-0112"
      ],
      "temporal_scope": "Claim made in this April 13, 2026 interview.",
      "topic_tags": [
        "catechon",
        "materialism",
        "history"
      ],
      "claim_type": "model",
      "confidence": "high"
    }
  ],
  "signature_moments": [
    {
      "refs": [
        "video:interview-n44of1y7zgo@transcript:v1#seg-0105"
      ],
      "moment": "Jiang's disagreement is not that the West is good, but that its pleasures are real enough to make people defend it.",
      "source_phrase": "this system is extremely attractive",
      "why_it_matters": "This is the public read's best hinge between Dugin's moral clarity and Jiang's social realism.",
      "tone": "reversal",
      "confidence": "high"
    },
    {
      "refs": [
        "video:interview-n44of1y7zgo@transcript:v1#seg-0107"
      ],
      "moment": "The new censorship is too much information, not too little.",
      "source_phrase": "not to blatantly censor, but to flood with so much information",
      "why_it_matters": "It connects eschatology to attention exhaustion and modern media.",
      "tone": "method",
      "confidence": "high"
    }
  ],
  "glossary_terms": [
    {
      "term": "information flooding",
      "refs": [
        "video:interview-n44of1y7zgo@transcript:v1#seg-0107",
        "video:interview-n44of1y7zgo@transcript:v1#seg-0108"
      ],
      "definition_or_usage": "A censorship-like strategy where algorithms overwhelm attention with too much information, draining the energy to care.",
      "confidence": "high"
    }
  ],
  "chronology_notes": [],
  "uncertainty_notes": []
}
