{
  "diarization": [
    {
      "speaker": "SPEAKER_00",
      "start": 4.773,
      "end": 23.875,
      "track": "A"
    },
    {
      "speaker": "SPEAKER_00",
      "start": 24.415,
      "end": 25.63,
      "track": "A"
    },
    {
      "speaker": "SPEAKER_00",
      "start": 25.799,
      "end": 30.625,
      "track": "A"
    },
    {
      "speaker": "SPEAKER_01",
      "start": 33.612,
      "end": 39.046,
      "track": "B"
    },
    {
      "speaker": "SPEAKER_00",
      "start": 39.13,
      "end": 39.603,
      "track": "A"
    },
    {
      "speaker": "SPEAKER_01",
      "start": 39.738,
      "end": 62.975,
      "track": "B"
    },
    {
      "speaker": "SPEAKER_01",
      "start": 63.565,
      "end": 78.247,
      "track": "B"
    },
    {
      "speaker": "SPEAKER_01",
      "start": 78.871,
      "end": 87.207,
      "track": "B"
    },
    {
      "speaker": "SPEAKER_01",
      "start": 87.899,
      "end": 96.995,
      "track": "B"
    },
    {
      "speaker": "SPEAKER_01",
      "start": 97.417,
      "end": 100.673,
      "track": "B"
    },
    {
      "speaker": "SPEAKER_01",
      "start": 101.433,
      "end": 109.887,
      "track": "B"
    },
    {
      "speaker": "SPEAKER_01",
      "start": 110.917,
      "end": 145.831,
      "track": "B"
    },
    {
      "speaker": "SPEAKER_01",
      "start": 146.219,
      "end": 152.48,
      "track": "B"
    },
    {
      "speaker": "SPEAKER_01",
      "start": 152.969,
      "end": 158.42,
      "track": "B"
    },
    {
      "speaker": "SPEAKER_01",
      "start": 158.977,
      "end": 180.796,
      "track": "B"
    },
    {
      "speaker": "SPEAKER_00",
      "start": 182.095,
      "end": 183.023,
      "track": "A"
    },
    {
      "speaker": "SPEAKER_00",
      "start": 183.648,
      "end": 205.855,
      "track": "A"
    },
    {
      "speaker": "SPEAKER_00",
      "start": 206.362,
      "end": 214.057,
      "track": "A"
    },
    {
      "speaker": "SPEAKER_00",
      "start": 214.36,
      "end": 220.874,
      "track": "A"
    },
    {
      "speaker": "SPEAKER_01",
      "start": 221.853,
      "end": 223.878,
      "track": "B"
    },
    {
      "speaker": "SPEAKER_01",
      "start": 224.249,
      "end": 226.73,
      "track": "B"
    },
    {
      "speaker": "SPEAKER_01",
      "start": 227.59,
      "end": 233.007,
      "track": "B"
    },
    {
      "speaker": "SPEAKER_01",
      "start": 233.53,
      "end": 255.586,
      "track": "B"
    },
    {
      "speaker": "SPEAKER_01",
      "start": 255.822,
      "end": 280.257,
      "track": "B"
    },
    {
      "speaker": "SPEAKER_01",
      "start": 280.561,
      "end": 310.244,
      "track": "B"
    },
    {
      "speaker": "SPEAKER_01",
      "start": 310.379,
      "end": 354.642,
      "track": "B"
    },
    {
      "speaker": "SPEAKER_00",
      "start": 356.127,
      "end": 363.4,
      "track": "A"
    },
    {
      "speaker": "SPEAKER_00",
      "start": 364.075,
      "end": 371.298,
      "track": "A"
    },
    {
      "speaker": "SPEAKER_00",
      "start": 372.8,
      "end": 372.968,
      "track": "A"
    },
    {
      "speaker": "SPEAKER_01",
      "start": 372.968,
      "end": 375.348,
      "track": "B"
    },
    {
      "speaker": "SPEAKER_01",
      "start": 375.668,
      "end": 377.896,
      "track": "B"
    },
    {
      "speaker": "SPEAKER_01",
      "start": 378.638,
      "end": 396.29,
      "track": "B"
    },
    {
      "speaker": "SPEAKER_00",
      "start": 396.492,
      "end": 396.796,
      "track": "A"
    },
    {
      "speaker": "SPEAKER_01",
      "start": 396.695,
      "end": 416.725,
      "track": "B"
    },
    {
      "speaker": "SPEAKER_01",
      "start": 417.046,
      "end": 451.454,
      "track": "B"
    },
    {
      "speaker": "SPEAKER_00",
      "start": 452.753,
      "end": 473.122,
      "track": "A"
    },
    {
      "speaker": "SPEAKER_00",
      "start": 473.493,
      "end": 479.045,
      "track": "A"
    },
    {
      "speaker": "SPEAKER_01",
      "start": 480.479,
      "end": 492.14,
      "track": "B"
    },
    {
      "speaker": "SPEAKER_01",
      "start": 492.258,
      "end": 495.886,
      "track": "B"
    },
    {
      "speaker": "SPEAKER_01",
      "start": 496.46,
      "end": 544.807,
      "track": "B"
    },
    {
      "speaker": "SPEAKER_01",
      "start": 544.823,
      "end": 611.868,
      "track": "B"
    },
    {
      "speaker": "SPEAKER_00",
      "start": 612.577,
      "end": 623.798,
      "track": "A"
    },
    {
      "speaker": "SPEAKER_00",
      "start": 624.473,
      "end": 628.085,
      "track": "A"
    },
    {
      "speaker": "SPEAKER_00",
      "start": 628.81,
      "end": 646.158,
      "track": "A"
    },
    {
      "speaker": "SPEAKER_00",
      "start": 646.597,
      "end": 648.166,
      "track": "A"
    },
    {
      "speaker": "SPEAKER_00",
      "start": 648.672,
      "end": 650.005,
      "track": "A"
    },
    {
      "speaker": "SPEAKER_00",
      "start": 650.545,
      "end": 651.811,
      "track": "A"
    },
    {
      "speaker": "SPEAKER_00",
      "start": 652.098,
      "end": 662.645,
      "track": "A"
    },
    {
      "speaker": "SPEAKER_00",
      "start": 663.353,
      "end": 668.922,
      "track": "A"
    },
    {
      "speaker": "SPEAKER_00",
      "start": 670.036,
      "end": 678.997,
      "track": "A"
    },
    {
      "speaker": "SPEAKER_00",
      "start": 679.823,
      "end": 686.962,
      "track": "A"
    },
    {
      "speaker": "SPEAKER_00",
      "start": 687.434,
      "end": 688.092,
      "track": "A"
    },
    {
      "speaker": "SPEAKER_00",
      "start": 688.953,
      "end": 705.676,
      "track": "A"
    },
    {
      "speaker": "SPEAKER_00",
      "start": 705.963,
      "end": 714.383,
      "track": "A"
    },
    {
      "speaker": "SPEAKER_00",
      "start": 715.16,
      "end": 716.341,
      "track": "A"
    },
    {
      "speaker": "SPEAKER_00",
      "start": 716.932,
      "end": 720.762,
      "track": "A"
    },
    {
      "speaker": "SPEAKER_00",
      "start": 721.032,
      "end": 721.606,
      "track": "A"
    },
    {
      "speaker": "SPEAKER_00",
      "start": 722.045,
      "end": 726.989,
      "track": "A"
    },
    {
      "speaker": "SPEAKER_01",
      "start": 727.158,
      "end": 727.192,
      "track": "B"
    },
    {
      "speaker": "SPEAKER_00",
      "start": 727.192,
      "end": 727.748,
      "track": "A"
    },
    {
      "speaker": "SPEAKER_01",
      "start": 730.178,
      "end": 731.832,
      "track": "B"
    },
    {
      "speaker": "SPEAKER_01",
      "start": 732.541,
      "end": 824.763,
      "track": "B"
    },
    {
      "speaker": "SPEAKER_01",
      "start": 825.202,
      "end": 828.543,
      "track": "B"
    },
    {
      "speaker": "SPEAKER_01",
      "start": 828.745,
      "end": 843.106,
      "track": "B"
    },
    {
      "speaker": "SPEAKER_00",
      "start": 841.013,
      "end": 841.722,
      "track": "A"
    },
    {
      "speaker": "SPEAKER_00",
      "start": 842.549,
      "end": 842.701,
      "track": "A"
    },
    {
      "speaker": "SPEAKER_01",
      "start": 843.46,
      "end": 889.715,
      "track": "B"
    },
    {
      "speaker": "SPEAKER_00",
      "start": 852.826,
      "end": 852.978,
      "track": "A"
    },
    {
      "speaker": "SPEAKER_00",
      "start": 890.963,
      "end": 909.357,
      "track": "A"
    },
    {
      "speaker": "SPEAKER_01",
      "start": 911.602,
      "end": 917.828,
      "track": "B"
    },
    {
      "speaker": "SPEAKER_01",
      "start": 918.115,
      "end": 959.746,
      "track": "B"
    },
    {
      "speaker": "SPEAKER_00",
      "start": 920.562,
      "end": 920.613,
      "track": "A"
    },
    {
      "speaker": "SPEAKER_00",
      "start": 961.045,
      "end": 989.395,
      "track": "A"
    },
    {
      "speaker": "SPEAKER_01",
      "start": 990.965,
      "end": 1081.668,
      "track": "B"
    },
    {
      "speaker": "SPEAKER_00",
      "start": 1081.668,
      "end": 1081.718,
      "track": "A"
    },
    {
      "speaker": "SPEAKER_00",
      "start": 1082.275,
      "end": 1091.607,
      "track": "A"
    },
    {
      "speaker": "SPEAKER_00",
      "start": 1092.569,
      "end": 1097.227,
      "track": "A"
    },
    {
      "speaker": "SPEAKER_00",
      "start": 1097.834,
      "end": 1101.277,
      "track": "A"
    },
    {
      "speaker": "SPEAKER_00",
      "start": 1101.817,
      "end": 1103.656,
      "track": "A"
    },
    {
      "speaker": "SPEAKER_01",
      "start": 1104.871,
      "end": 1119.367,
      "track": "B"
    },
    {
      "speaker": "SPEAKER_01",
      "start": 1119.974,
      "end": 1136.461,
      "track": "B"
    },
    {
      "speaker": "SPEAKER_01",
      "start": 1137.018,
      "end": 1159.934,
      "track": "B"
    },
    {
      "speaker": "SPEAKER_01",
      "start": 1160.761,
      "end": 1180.825,
      "track": "B"
    },
    {
      "speaker": "SPEAKER_00",
      "start": 1181.129,
      "end": 1185.112,
      "track": "A"
    },
    {
      "speaker": "SPEAKER_00",
      "start": 1186.141,
      "end": 1188.622,
      "track": "A"
    },
    {
      "speaker": "SPEAKER_00",
      "start": 1189.752,
      "end": 1190.815,
      "track": "A"
    },
    {
      "speaker": "SPEAKER_01",
      "start": 1190.815,
      "end": 1190.832,
      "track": "B"
    },
    {
      "speaker": "SPEAKER_01",
      "start": 1192.435,
      "end": 1209.884,
      "track": "B"
    },
    {
      "speaker": "SPEAKER_00",
      "start": 1210.88,
      "end": 1211.386,
      "track": "A"
    },
    {
      "speaker": "SPEAKER_00",
      "start": 1212.095,
      "end": 1214.727,
      "track": "A"
    },
    {
      "speaker": "SPEAKER_00",
      "start": 1215.115,
      "end": 1221.342,
      "track": "A"
    },
    {
      "speaker": "SPEAKER_00",
      "start": 1221.494,
      "end": 1225.342,
      "track": "A"
    },
    {
      "speaker": "SPEAKER_01",
      "start": 1226.894,
      "end": 1306.898,
      "track": "B"
    },
    {
      "speaker": "SPEAKER_01",
      "start": 1307.32,
      "end": 1369.876,
      "track": "B"
    },
    {
      "speaker": "SPEAKER_00",
      "start": 1370.5,
      "end": 1370.905,
      "track": "A"
    },
    {
      "speaker": "SPEAKER_00",
      "start": 1371.378,
      "end": 1405.28,
      "track": "A"
    },
    {
      "speaker": "SPEAKER_00",
      "start": 1405.938,
      "end": 1422.205,
      "track": "A"
    },
    {
      "speaker": "SPEAKER_00",
      "start": 1422.982,
      "end": 1447.012,
      "track": "A"
    },
    {
      "speaker": "SPEAKER_00",
      "start": 1447.636,
      "end": 1460.528,
      "track": "A"
    },
    {
      "speaker": "SPEAKER_00",
      "start": 1461.271,
      "end": 1465.642,
      "track": "A"
    },
    {
      "speaker": "SPEAKER_00",
      "start": 1466.249,
      "end": 1467.211,
      "track": "A"
    },
    {
      "speaker": "SPEAKER_01",
      "start": 1467.532,
      "end": 1467.903,
      "track": "B"
    },
    {
      "speaker": "SPEAKER_01",
      "start": 1468.325,
      "end": 1476.34,
      "track": "B"
    },
    {
      "speaker": "SPEAKER_01",
      "start": 1476.627,
      "end": 1478.99,
      "track": "B"
    },
    {
      "speaker": "SPEAKER_01",
      "start": 1479.648,
      "end": 1489.081,
      "track": "B"
    },
    {
      "speaker": "SPEAKER_00",
      "start": 1490.195,
      "end": 1491.528,
      "track": "A"
    },
    {
      "speaker": "SPEAKER_01",
      "start": 1494.278,
      "end": 1518.747,
      "track": "B"
    },
    {
      "speaker": "SPEAKER_00",
      "start": 1516.604,
      "end": 1516.942,
      "track": "A"
    },
    {
      "speaker": "SPEAKER_00",
      "start": 1518.747,
      "end": 1518.764,
      "track": "A"
    },
    {
      "speaker": "SPEAKER_00",
      "start": 1520.367,
      "end": 1525.025,
      "track": "A"
    },
    {
      "speaker": "SPEAKER_00",
      "start": 1525.632,
      "end": 1527.556,
      "track": "A"
    },
    {
      "speaker": "SPEAKER_01",
      "start": 1529.041,
      "end": 1554.623,
      "track": "B"
    },
    {
      "speaker": "SPEAKER_01",
      "start": 1554.927,
      "end": 1558.167,
      "track": "B"
    },
    {
      "speaker": "SPEAKER_01",
      "start": 1558.859,
      "end": 1629.093,
      "track": "B"
    },
    {
      "speaker": "SPEAKER_00",
      "start": 1630.544,
      "end": 1631.135,
      "track": "A"
    },
    {
      "speaker": "SPEAKER_00",
      "start": 1631.708,
      "end": 1632.13,
      "track": "A"
    },
    {
      "speaker": "SPEAKER_00",
      "start": 1632.383,
      "end": 1633.042,
      "track": "A"
    },
    {
      "speaker": "SPEAKER_01",
      "start": 1636.332,
      "end": 1709.148,
      "track": "B"
    },
    {
      "speaker": "SPEAKER_01",
      "start": 1709.468,
      "end": 1735.405,
      "track": "B"
    },
    {
      "speaker": "SPEAKER_01",
      "start": 1735.642,
      "end": 1745.48,
      "track": "B"
    },
    {
      "speaker": "SPEAKER_01",
      "start": 1745.648,
      "end": 1784.427,
      "track": "B"
    },
    {
      "speaker": "SPEAKER_01",
      "start": 1784.883,
      "end": 1795.582,
      "track": "B"
    },
    {
      "speaker": "SPEAKER_00",
      "start": 1797.185,
      "end": 1799.547,
      "track": "A"
    },
    {
      "speaker": "SPEAKER_00",
      "start": 1802.129,
      "end": 1802.146,
      "track": "A"
    },
    {
      "speaker": "SPEAKER_01",
      "start": 1802.146,
      "end": 1802.247,
      "track": "B"
    },
    {
      "speaker": "SPEAKER_00",
      "start": 1802.247,
      "end": 1802.888,
      "track": "A"
    },
    {
      "speaker": "SPEAKER_01",
      "start": 1802.888,
      "end": 1802.939,
      "track": "B"
    },
    {
      "speaker": "SPEAKER_01",
      "start": 1803.361,
      "end": 1807.613,
      "track": "B"
    },
    {
      "speaker": "SPEAKER_01",
      "start": 1807.664,
      "end": 1833.044,
      "track": "B"
    },
    {
      "speaker": "SPEAKER_01",
      "start": 1833.398,
      "end": 1854.914,
      "track": "B"
    },
    {
      "speaker": "SPEAKER_01",
      "start": 1855.471,
      "end": 1906.754,
      "track": "B"
    },
    {
      "speaker": "SPEAKER_00",
      "start": 1907.362,
      "end": 1913.285,
      "track": "A"
    },
    {
      "speaker": "SPEAKER_00",
      "start": 1913.943,
      "end": 1921.418,
      "track": "A"
    },
    {
      "speaker": "SPEAKER_00",
      "start": 1921.874,
      "end": 1924.085,
      "track": "A"
    },
    {
      "speaker": "SPEAKER_00",
      "start": 1924.422,
      "end": 1930.852,
      "track": "A"
    },
    {
      "speaker": "SPEAKER_00",
      "start": 1931.375,
      "end": 1939.677,
      "track": "A"
    },
    {
      "speaker": "SPEAKER_00",
      "start": 1940.268,
      "end": 1947.423,
      "track": "A"
    },
    {
      "speaker": "SPEAKER_00",
      "start": 1948.098,
      "end": 1961.463,
      "track": "A"
    },
    {
      "speaker": "SPEAKER_00",
      "start": 1961.733,
      "end": 1966.188,
      "track": "A"
    },
    {
      "speaker": "SPEAKER_00",
      "start": 1966.424,
      "end": 1972.651,
      "track": "A"
    },
    {
      "speaker": "SPEAKER_00",
      "start": 1975.267,
      "end": 1984.97,
      "track": "A"
    },
    {
      "speaker": "SPEAKER_01",
      "start": 1987.619,
      "end": 1988.767,
      "track": "B"
    },
    {
      "speaker": "SPEAKER_01",
      "start": 1989.543,
      "end": 1991.028,
      "track": "B"
    },
    {
      "speaker": "SPEAKER_01",
      "start": 1991.753,
      "end": 2004.663,
      "track": "B"
    },
    {
      "speaker": "SPEAKER_01",
      "start": 2005.118,
      "end": 2013.033,
      "track": "B"
    },
    {
      "speaker": "SPEAKER_01",
      "start": 2014.045,
      "end": 2053.837,
      "track": "B"
    },
    {
      "speaker": "SPEAKER_01",
      "start": 2054.782,
      "end": 2057.313,
      "track": "B"
    },
    {
      "speaker": "SPEAKER_01",
      "start": 2057.903,
      "end": 2112.325,
      "track": "B"
    },
    {
      "speaker": "SPEAKER_01",
      "start": 2112.646,
      "end": 2150.412,
      "track": "B"
    },
    {
      "speaker": "SPEAKER_01",
      "start": 2150.564,
      "end": 2152.927,
      "track": "B"
    },
    {
      "speaker": "SPEAKER_01",
      "start": 2153.399,
      "end": 2206.133,
      "track": "B"
    },
    {
      "speaker": "SPEAKER_00",
      "start": 2206.775,
      "end": 2212.343,
      "track": "A"
    },
    {
      "speaker": "SPEAKER_01",
      "start": 2216.292,
      "end": 2217.575,
      "track": "B"
    },
    {
      "speaker": "SPEAKER_00",
      "start": 2218.064,
      "end": 2218.25,
      "track": "A"
    },
    {
      "speaker": "SPEAKER_00",
      "start": 2218.553,
      "end": 2227.531,
      "track": "A"
    },
    {
      "speaker": "SPEAKER_01",
      "start": 2230.552,
      "end": 2288.838,
      "track": "B"
    },
    {
      "speaker": "SPEAKER_00",
      "start": 2290.694,
      "end": 2301.157,
      "track": "A"
    },
    {
      "speaker": "SPEAKER_00",
      "start": 2301.207,
      "end": 2307.451,
      "track": "A"
    },
    {
      "speaker": "SPEAKER_00",
      "start": 2309.02,
      "end": 2309.037,
      "track": "A"
    },
    {
      "speaker": "SPEAKER_01",
      "start": 2309.037,
      "end": 2327.178,
      "track": "B"
    },
    {
      "speaker": "SPEAKER_00",
      "start": 2310.387,
      "end": 2311.45,
      "track": "A"
    },
    {
      "speaker": "SPEAKER_00",
      "start": 2327.178,
      "end": 2328.089,
      "track": "A"
    },
    {
      "speaker": "SPEAKER_00",
      "start": 2329.557,
      "end": 2335.565,
      "track": "A"
    },
    {
      "speaker": "SPEAKER_00",
      "start": 2336.054,
      "end": 2337.134,
      "track": "A"
    },
    {
      "speaker": "SPEAKER_00",
      "start": 2337.421,
      "end": 2342.348,
      "track": "A"
    },
    {
      "speaker": "SPEAKER_01",
      "start": 2344.593,
      "end": 2348.44,
      "track": "B"
    },
    {
      "speaker": "SPEAKER_01",
      "start": 2348.98,
      "end": 2353.435,
      "track": "B"
    },
    {
      "speaker": "SPEAKER_01",
      "start": 2353.57,
      "end": 2421.661,
      "track": "B"
    },
    {
      "speaker": "SPEAKER_00",
      "start": 2421.661,
      "end": 2421.914,
      "track": "A"
    },
    {
      "speaker": "SPEAKER_01",
      "start": 2421.914,
      "end": 2426.656,
      "track": "B"
    },
    {
      "speaker": "SPEAKER_00",
      "start": 2428.9,
      "end": 2453.487,
      "track": "A"
    },
    {
      "speaker": "SPEAKER_00",
      "start": 2453.74,
      "end": 2454.398,
      "track": "A"
    },
    {
      "speaker": "SPEAKER_00",
      "start": 2454.77,
      "end": 2456.93,
      "track": "A"
    },
    {
      "speaker": "SPEAKER_00",
      "start": 2457.605,
      "end": 2464.372,
      "track": "A"
    },
    {
      "speaker": "SPEAKER_00",
      "start": 2465.182,
      "end": 2468.168,
      "track": "A"
    },
    {
      "speaker": "SPEAKER_00",
      "start": 2468.978,
      "end": 2472.758,
      "track": "A"
    },
    {
      "speaker": "SPEAKER_00",
      "start": 2473.13,
      "end": 2487.305,
      "track": "A"
    },
    {
      "speaker": "SPEAKER_01",
      "start": 2487.305,
      "end": 2487.322,
      "track": "B"
    },
    {
      "speaker": "SPEAKER_00",
      "start": 2488.621,
      "end": 2488.975,
      "track": "A"
    },
    {
      "speaker": "SPEAKER_01",
      "start": 2488.975,
      "end": 2490.528,
      "track": "B"
    },
    {
      "speaker": "SPEAKER_01",
      "start": 2490.916,
      "end": 2529.155,
      "track": "B"
    },
    {
      "speaker": "SPEAKER_00",
      "start": 2498.915,
      "end": 2499.067,
      "track": "A"
    },
    {
      "speaker": "SPEAKER_01",
      "start": 2529.458,
      "end": 2604.198,
      "track": "B"
    },
    {
      "speaker": "SPEAKER_01",
      "start": 2604.62,
      "end": 2679.68,
      "track": "B"
    },
    {
      "speaker": "SPEAKER_01",
      "start": 2680.321,
      "end": 2701.904,
      "track": "B"
    },
    {
      "speaker": "SPEAKER_00",
      "start": 2703.44,
      "end": 2706.528,
      "track": "A"
    },
    {
      "speaker": "SPEAKER_01",
      "start": 2709.464,
      "end": 2739.113,
      "track": "B"
    },
    {
      "speaker": "SPEAKER_01",
      "start": 2739.873,
      "end": 2767.109,
      "track": "B"
    },
    {
      "speaker": "SPEAKER_01",
      "start": 2767.666,
      "end": 2769.742,
      "track": "B"
    },
    {
      "speaker": "SPEAKER_01",
      "start": 2770.062,
      "end": 2819.945,
      "track": "B"
    },
    {
      "speaker": "SPEAKER_01",
      "start": 2820.248,
      "end": 2861.693,
      "track": "B"
    },
    {
      "speaker": "SPEAKER_01",
      "start": 2862.132,
      "end": 2880.745,
      "track": "B"
    },
    {
      "speaker": "SPEAKER_00",
      "start": 2881.319,
      "end": 2885.453,
      "track": "A"
    },
    {
      "speaker": "SPEAKER_00",
      "start": 2885.791,
      "end": 2891.748,
      "track": "A"
    },
    {
      "speaker": "SPEAKER_00",
      "start": 2892.271,
      "end": 2912.774,
      "track": "A"
    },
    {
      "speaker": "SPEAKER_00",
      "start": 2913.28,
      "end": 2919.71,
      "track": "A"
    },
    {
      "speaker": "SPEAKER_00",
      "start": 2919.963,
      "end": 2921.026,
      "track": "A"
    },
    {
      "speaker": "SPEAKER_01",
      "start": 2921.026,
      "end": 2932.45,
      "track": "B"
    },
    {
      "speaker": "SPEAKER_01",
      "start": 2932.568,
      "end": 2940.567,
      "track": "B"
    },
    {
      "speaker": "SPEAKER_01",
      "start": 2941.225,
      "end": 2947.638,
      "track": "B"
    },
    {
      "speaker": "SPEAKER_00",
      "start": 2947.638,
      "end": 2948.043,
      "track": "A"
    },
    {
      "speaker": "SPEAKER_01",
      "start": 2948.043,
      "end": 3045.428,
      "track": "B"
    },
    {
      "speaker": "SPEAKER_00",
      "start": 3046.812,
      "end": 3049.023,
      "track": "A"
    },
    {
      "speaker": "SPEAKER_00",
      "start": 3049.276,
      "end": 3050.879,
      "track": "A"
    },
    {
      "speaker": "SPEAKER_01",
      "start": 3053.09,
      "end": 3086.654,
      "track": "B"
    },
    {
      "speaker": "SPEAKER_00",
      "start": 3087.295,
      "end": 3110.363,
      "track": "A"
    },
    {
      "speaker": "SPEAKER_00",
      "start": 3111.241,
      "end": 3119.02,
      "track": "A"
    },
    {
      "speaker": "SPEAKER_00",
      "start": 3119.847,
      "end": 3133.752,
      "track": "A"
    },
    {
      "speaker": "SPEAKER_00",
      "start": 3135.322,
      "end": 3135.338,
      "track": "A"
    },
    {
      "speaker": "SPEAKER_01",
      "start": 3135.338,
      "end": 3135.372,
      "track": "B"
    },
    {
      "speaker": "SPEAKER_00",
      "start": 3135.372,
      "end": 3135.524,
      "track": "A"
    },
    {
      "speaker": "SPEAKER_01",
      "start": 3135.524,
      "end": 3155.842,
      "track": "B"
    },
    {
      "speaker": "SPEAKER_01",
      "start": 3156.314,
      "end": 3178.015,
      "track": "B"
    },
    {
      "speaker": "SPEAKER_01",
      "start": 3178.623,
      "end": 3181.863,
      "track": "B"
    },
    {
      "speaker": "SPEAKER_01",
      "start": 3182.504,
      "end": 3191.38,
      "track": "B"
    },
    {
      "speaker": "SPEAKER_01",
      "start": 3191.768,
      "end": 3200.543,
      "track": "B"
    },
    {
      "speaker": "SPEAKER_01",
      "start": 3201.1,
      "end": 3268.448,
      "track": "B"
    },
    {
      "speaker": "SPEAKER_00",
      "start": 3269.967,
      "end": 3274.793,
      "track": "A"
    },
    {
      "speaker": "SPEAKER_00",
      "start": 3275.789,
      "end": 3289.036,
      "track": "A"
    },
    {
      "speaker": "SPEAKER_00",
      "start": 3289.39,
      "end": 3295.094,
      "track": "A"
    },
    {
      "speaker": "SPEAKER_00",
      "start": 3295.769,
      "end": 3297.17,
      "track": "A"
    },
    {
      "speaker": "SPEAKER_00",
      "start": 3297.946,
      "end": 3298.503,
      "track": "A"
    },
    {
      "speaker": "SPEAKER_01",
      "start": 3298.503,
      "end": 3298.52,
      "track": "B"
    },
    {
      "speaker": "SPEAKER_00",
      "start": 3300.038,
      "end": 3300.055,
      "track": "A"
    },
    {
      "speaker": "SPEAKER_01",
      "start": 3300.055,
      "end": 3314.534,
      "track": "B"
    },
    {
      "speaker": "SPEAKER_01",
      "start": 3314.855,
      "end": 3391.315,
      "track": "B"
    },
    {
      "speaker": "SPEAKER_01",
      "start": 3391.703,
      "end": 3432.507,
      "track": "B"
    },
    {
      "speaker": "SPEAKER_01",
      "start": 3432.862,
      "end": 3452.96,
      "track": "B"
    },
    {
      "speaker": "SPEAKER_00",
      "start": 3454.006,
      "end": 3464.873,
      "track": "A"
    },
    {
      "speaker": "SPEAKER_00",
      "start": 3465.228,
      "end": 3484.195,
      "track": "A"
    },
    {
      "speaker": "SPEAKER_00",
      "start": 3484.465,
      "end": 3489.292,
      "track": "A"
    },
    {
      "speaker": "SPEAKER_00",
      "start": 3489.494,
      "end": 3495.755,
      "track": "A"
    },
    {
      "speaker": "SPEAKER_01",
      "start": 3490.355,
      "end": 3491.249,
      "track": "B"
    },
    {
      "speaker": "SPEAKER_01",
      "start": 3497.088,
      "end": 3518.047,
      "track": "B"
    },
    {
      "speaker": "SPEAKER_01",
      "start": 3518.384,
      "end": 3548.573,
      "track": "B"
    },
    {
      "speaker": "SPEAKER_01",
      "start": 3549.248,
      "end": 3558.175,
      "track": "B"
    },
    {
      "speaker": "SPEAKER_01",
      "start": 3558.327,
      "end": 3577.025,
      "track": "B"
    },
    {
      "speaker": "SPEAKER_01",
      "start": 3577.97,
      "end": 3620.748,
      "track": "B"
    },
    {
      "speaker": "SPEAKER_00",
      "start": 3622.267,
      "end": 3633.826,
      "track": "A"
    },
    {
      "speaker": "SPEAKER_00",
      "start": 3634.636,
      "end": 3636.037,
      "track": "A"
    },
    {
      "speaker": "SPEAKER_00",
      "start": 3637.657,
      "end": 3647.039,
      "track": "A"
    },
    {
      "speaker": "SPEAKER_00",
      "start": 3647.191,
      "end": 3661.805,
      "track": "A"
    },
    {
      "speaker": "SPEAKER_01",
      "start": 3663.728,
      "end": 3688.096,
      "track": "B"
    },
    {
      "speaker": "SPEAKER_01",
      "start": 3688.906,
      "end": 3714.539,
      "track": "B"
    },
    {
      "speaker": "SPEAKER_00",
      "start": 3714.539,
      "end": 3714.742,
      "track": "A"
    },
    {
      "speaker": "SPEAKER_01",
      "start": 3714.742,
      "end": 3756.862,
      "track": "B"
    },
    {
      "speaker": "SPEAKER_01",
      "start": 3757.385,
      "end": 3770.918,
      "track": "B"
    },
    {
      "speaker": "SPEAKER_00",
      "start": 3771.931,
      "end": 3775.475,
      "track": "A"
    },
    {
      "speaker": "SPEAKER_00",
      "start": 3776.69,
      "end": 3778.495,
      "track": "A"
    },
    {
      "speaker": "SPEAKER_01",
      "start": 3778.495,
      "end": 3778.529,
      "track": "B"
    },
    {
      "speaker": "SPEAKER_01",
      "start": 3781.651,
      "end": 3809.309,
      "track": "B"
    },
    {
      "speaker": "SPEAKER_01",
      "start": 3809.579,
      "end": 3825.543,
      "track": "B"
    },
    {
      "speaker": "SPEAKER_01",
      "start": 3826.015,
      "end": 3826.64,
      "track": "B"
    },
    {
      "speaker": "SPEAKER_01",
      "start": 3826.91,
      "end": 3828.8,
      "track": "B"
    },
    {
      "speaker": "SPEAKER_00",
      "start": 3830.42,
      "end": 3849.961,
      "track": "A"
    },
    {
      "speaker": "SPEAKER_00",
      "start": 3850.754,
      "end": 3860.17,
      "track": "A"
    },
    {
      "speaker": "SPEAKER_00",
      "start": 3860.896,
      "end": 3862.347,
      "track": "A"
    },
    {
      "speaker": "SPEAKER_00",
      "start": 3862.533,
      "end": 3862.972,
      "track": "A"
    },
    {
      "speaker": "SPEAKER_01",
      "start": 3862.972,
      "end": 3863.191,
      "track": "B"
    },
    {
      "speaker": "SPEAKER_00",
      "start": 3863.191,
      "end": 3863.461,
      "track": "A"
    },
    {
      "speaker": "SPEAKER_01",
      "start": 3863.461,
      "end": 3863.697,
      "track": "B"
    },
    {
      "speaker": "SPEAKER_00",
      "start": 3863.697,
      "end": 3863.714,
      "track": "A"
    },
    {
      "speaker": "SPEAKER_01",
      "start": 3863.714,
      "end": 3863.731,
      "track": "B"
    },
    {
      "speaker": "SPEAKER_00",
      "start": 3863.731,
      "end": 3863.967,
      "track": "A"
    },
    {
      "speaker": "SPEAKER_01",
      "start": 3863.967,
      "end": 3864.119,
      "track": "B"
    },
    {
      "speaker": "SPEAKER_01",
      "start": 3867.578,
      "end": 3871.882,
      "track": "B"
    },
    {
      "speaker": "SPEAKER_01",
      "start": 3871.898,
      "end": 3887.643,
      "track": "B"
    },
    {
      "speaker": "SPEAKER_00",
      "start": 3887.643,
      "end": 3887.997,
      "track": "A"
    },
    {
      "speaker": "SPEAKER_01",
      "start": 3887.997,
      "end": 3931.045,
      "track": "B"
    },
    {
      "speaker": "SPEAKER_01",
      "start": 3931.248,
      "end": 3952.915,
      "track": "B"
    },
    {
      "speaker": "SPEAKER_01",
      "start": 3953.641,
      "end": 3954.299,
      "track": "B"
    },
    {
      "speaker": "SPEAKER_01",
      "start": 3954.923,
      "end": 3968.98,
      "track": "B"
    },
    {
      "speaker": "SPEAKER_01",
      "start": 3969.74,
      "end": 3982.092,
      "track": "B"
    },
    {
      "speaker": "SPEAKER_01",
      "start": 3982.565,
      "end": 3982.598,
      "track": "B"
    },
    {
      "speaker": "SPEAKER_00",
      "start": 3982.598,
      "end": 3982.632,
      "track": "A"
    },
    {
      "speaker": "SPEAKER_01",
      "start": 3982.632,
      "end": 3982.953,
      "track": "B"
    },
    {
      "speaker": "SPEAKER_00",
      "start": 3983.577,
      "end": 3995.238,
      "track": "A"
    },
    {
      "speaker": "SPEAKER_00",
      "start": 3995.474,
      "end": 4003.439,
      "track": "A"
    },
    {
      "speaker": "SPEAKER_00",
      "start": 4004.03,
      "end": 4007.033,
      "track": "A"
    },
    {
      "speaker": "SPEAKER_00",
      "start": 4007.827,
      "end": 4009.497,
      "track": "A"
    },
    {
      "speaker": "SPEAKER_01",
      "start": 4011.134,
      "end": 4012.147,
      "track": "B"
    },
    {
      "speaker": "SPEAKER_01",
      "start": 4012.94,
      "end": 4014.239,
      "track": "B"
    },
    {
      "speaker": "SPEAKER_01",
      "start": 4014.863,
      "end": 4015.505,
      "track": "B"
    },
    {
      "speaker": "SPEAKER_01",
      "start": 4016.129,
      "end": 4016.905,
      "track": "B"
    },
    {
      "speaker": "SPEAKER_01",
      "start": 4017.243,
      "end": 4056.038,
      "track": "B"
    },
    {
      "speaker": "SPEAKER_00",
      "start": 4056.038,
      "end": 4057.186,
      "track": "A"
    },
    {
      "speaker": "SPEAKER_00",
      "start": 4058.333,
      "end": 4083.123,
      "track": "A"
    },
    {
      "speaker": "SPEAKER_01",
      "start": 4066.028,
      "end": 4068.678,
      "track": "B"
    },
    {
      "speaker": "SPEAKER_00",
      "start": 4083.663,
      "end": 4084.051,
      "track": "A"
    },
    {
      "speaker": "SPEAKER_00",
      "start": 4085.705,
      "end": 4085.975,
      "track": "A"
    },
    {
      "speaker": "SPEAKER_01",
      "start": 4085.975,
      "end": 4087.19,
      "track": "B"
    },
    {
      "speaker": "SPEAKER_00",
      "start": 4087.19,
      "end": 4087.207,
      "track": "A"
    }
  ],
  "embeddings": {
    "SPEAKER_00": [
      -0.2519696056842804,
      -0.34178727865219116,
      -0.07152488082647324,
      -0.28547734022140503,
      -0.18435584008693695,
      -0.1271427720785141,
      0.046231161803007126,
      -0.38425934314727783,
      0.051312584429979324,
      0.4295789897441864,
      0.14884085953235626,
      0.29729267954826355,
      0.3290449380874634,
      0.30646800994873047,
      -0.3321116864681244,
      -0.15163619816303253,
      0.12828394770622253,
      0.08884573727846146,
      0.1348351687192917,
      -0.2822195887565613,
      -0.13190966844558716,
      0.16253942251205444,
      0.21995224058628082,
      0.010650322772562504,
      0.08072774857282639,
      -0.09939155727624893,
      0.19094789028167725,
      0.09158837050199509,
      -0.33004292845726013,
      -0.3035535514354706,
      0.14472270011901855,
      0.09287435561418533,
      -0.4146749973297119,
      -0.4696579575538635,
      -0.009499942883849144,
      -0.32065069675445557,
      0.18031083047389984,
      -0.09939534217119217,
      0.02290397509932518,
      0.362853467464447,
      -0.048112183809280396,
      0.1603437215089798,
      0.014112532138824463,
      0.3647151589393616,
      0.025953035801649094,
      -0.10281579196453094,
      0.14615267515182495,
      0.01140439510345459,
      0.34106117486953735,
      0.20072929561138153,
      0.13289299607276917,
      -0.08702287077903748,
      0.3211321234703064,
      0.0319707915186882,
      0.2179098278284073,
      -0.23164156079292297,
      -0.1066807210445404,
      0.07377348095178604,
      -0.03203629329800606,
      0.3929448127746582,
      0.18613865971565247,
      -0.05396799370646477,
      0.23762324452400208,
      0.27314773201942444,
      0.4370567798614502,
      -0.1867540180683136,
      -0.035994596779346466,
      -0.040468934923410416,
      -0.13126611709594727,
      0.057619959115982056,
      0.09572851657867432,
      -0.07951736450195312,
      0.28864824771881104,
      -0.28928765654563904,
      -0.26725897192955017,
      0.27590057253837585,
      -0.43941476941108704,
      -0.4083321988582611,
      -0.2329886555671692,
      -0.17435084283351898,
      -0.3458203673362732,
      -0.1913672536611557,
      0.11491260677576065,
      -0.29130813479423523,
      -0.021817993372678757,
      -0.027486348524689674,
      -0.1579855978488922,
      -0.13795796036720276,
      -0.5539024472236633,
      -0.07394956052303314,
      0.22374123334884644,
      0.004982606042176485,
      0.21824520826339722,
      -0.04040485620498657,
      -0.4044822156429291,
      0.12523536384105682,
      -0.19378574192523956,
      0.07049211859703064,
      0.10859186202287674,
      -0.04666240140795708,
      -0.18661151826381683,
      0.04769526794552803,
      0.39849328994750977,
      0.3608122766017914,
      -0.11671501398086548,
      0.2954445779323578,
      0.40083566308021545,
      -0.3010171353816986,
      -0.21535031497478485,
      0.10006267577409744,
      -0.33694207668304443,
      0.08399244397878647,
      -0.2469434142112732,
      -0.3108448386192322,
      0.1096218079328537,
      0.05891310051083565,
      0.07051199674606323,
      0.2527548670768738,
      -0.15736030042171478,
      0.10480700433254242,
      -0.2763790190219879,
      0.06236309930682182,
      0.10318484157323837,
      0.29114168882369995,
      -0.18490155041217804,
      -0.09732504934072495,
      -0.2714480757713318,
      -0.21758142113685608,
      -0.08347596973180771,
      0.2586326599121094,
      -0.27081099152565,
      0.17664843797683716,
      0.14271071553230286,
      -0.08086615055799484,
      -0.06155991926789284,
      -0.32061246037483215,
      -0.5036860704421997,
      0.3522188663482666,
      0.31468629837036133,
      -0.34258463978767395,
      -0.20392923057079315,
      0.3570536971092224,
      0.5934297442436218,
      0.05593481659889221,
      -0.38487333059310913,
      -0.2545050084590912,
      0.08259647339582443,
      -0.07323501259088516,
      0.1567743867635727,
      -0.29628121852874756,
      0.3299504816532135,
      0.026418525725603104,
      0.34698453545570374,
      0.1414552628993988,
      -0.12373238801956177,
      0.05765751004219055,
      0.16190683841705322,
      0.15102225542068481,
      -0.11025460809469223,
      0.13512611389160156,
      0.16923056542873383,
      0.03657270967960358,
      -0.11222435534000397,
      -0.32598575949668884,
      -0.24940191209316254,
      0.02249401994049549,
      -0.3835374414920807,
      -0.2515563666820526,
      -0.14792384207248688,
      0.2580987811088562,
      0.0785798579454422,
      0.036529358476400375,
      -0.5422401428222656,
      0.12210951745510101,
      -0.16407716274261475,
      -0.18724177777767181,
      -0.5604485869407654,
      -0.04144720360636711,
      -0.13806577026844025,
      0.17515228688716888,
      -0.4625944197177887,
      0.4340408444404602,
      0.19096533954143524,
      -0.41306278109550476,
      0.07540182769298553,
      0.33666911721229553,
      0.424426794052124,
      0.014708737842738628,
      0.2325785607099533,
      -0.3769547939300537,
      -0.43140482902526855,
      0.3643660843372345,
      -0.048155929893255234,
      -0.26641497015953064,
      -0.286348819732666,
      0.02641753852367401,
      0.027173632755875587,
      -0.2881583869457245,
      0.2619815468788147,
      0.08155575394630432,
      -0.10818694531917572,
      0.15307684242725372,
      -0.508355438709259,
      -0.49058565497398376,
      0.17347174882888794,
      0.17643329501152039,
      0.1061464250087738,
      -0.3904871940612793,
      -0.6152326464653015,
      -0.16716045141220093,
      -0.05644414573907852,
      -0.054299529641866684,
      0.008917154744267464,
      -0.02685343101620674,
      -0.02446422353386879,
      0.4501725435256958,
      -0.1289522498846054,
      -0.31356754899024963,
      0.19557586312294006,
      -0.02539854124188423,
      0.22524788975715637,
      0.10418649762868881,
      -0.11057791113853455,
      0.35898345708847046,
      -0.24472612142562866,
      0.14065757393836975,
      0.1692643016576767,
      0.022335128858685493,
      -0.370891273021698,
      -0.08794635534286499,
      -0.29939746856689453,
      0.1679917722940445,
      0.45331916213035583,
      0.1837438941001892,
      0.011800244450569153,
      0.3538883924484253,
      0.04460426792502403,
      0.18132396042346954,
      0.07117290049791336,
      -0.10807577520608902,
      -0.3796224892139435,
      0.20215214788913727,
      0.2699146866798401,
      0.10836557298898697,
      -0.07869978249073029,
      -0.29037103056907654,
      0.2456384003162384,
      -0.0664244145154953,
      -0.12076720595359802,
      -0.27216681838035583,
      -0.05930974334478378,
      0.14291076362133026,
      0.26398766040802,
      -0.10432349890470505,
      0.15185503661632538,
      -0.43957361578941345
    ],
    "SPEAKER_01": [
      -0.2723863124847412,
      0.04821336269378662,
      -0.11713163554668427,
      -0.17075055837631226,
      0.15556886792182922,
      0.034337908029556274,
      0.06678478419780731,
      0.017111802473664284,
      0.05799949914216995,
      0.004922321066260338,
      0.22006770968437195,
      -0.07364875078201294,
      -0.25483688712120056,
      0.1626892238855362,
      -0.1506606489419937,
      -0.14477941393852234,
      0.07568114995956421,
      0.01631467044353485,
      -0.21850061416625977,
      -0.04522418603301048,
      -0.3358258008956909,
      -0.014723099768161774,
      0.43224719166755676,
      -0.310636043548584,
      -0.16584554314613342,
      0.09289440512657166,
      -0.11747530102729797,
      -0.32015931606292725,
      -0.08203031122684479,
      0.3264527916908264,
      0.2202315330505371,
      0.21454763412475586,
      0.06865034997463226,
      -0.2063015252351761,
      -0.20234331488609314,
      0.08601934462785721,
      0.3406412899494171,
      -0.11976118385791779,
      0.18666164577007294,
      -0.2846728265285492,
      0.35413628816604614,
      0.04708094522356987,
      -0.013925712555646896,
      -0.05168444290757179,
      -0.1758263111114502,
      0.3402423858642578,
      0.3790264129638672,
      0.11413294076919556,
      -0.26737311482429504,
      0.1631847769021988,
      0.2190062552690506,
      -0.06116980314254761,
      0.4186607301235199,
      0.06517153233289719,
      -0.39149442315101624,
      0.36726194620132446,
      0.2613295912742615,
      -0.07121481746435165,
      -0.3808180093765259,
      -0.024982018396258354,
      0.29697385430336,
      -0.12573683261871338,
      0.2726867198944092,
      0.2676418125629425,
      0.10592357069253922,
      0.14517347514629364,
      0.19666129350662231,
      -0.29392680525779724,
      -0.19044382870197296,
      -0.1132788434624672,
      0.35964736342430115,
      -0.15196509659290314,
      0.3134872317314148,
      -0.2661059498786926,
      -0.16287150979042053,
      -0.01930605247616768,
      0.026067767292261124,
      -0.06990160793066025,
      0.13325034081935883,
      -0.2258303463459015,
      0.12869124114513397,
      0.12169113755226135,
      0.10840056836605072,
      -0.15319105982780457,
      -0.04811406508088112,
      -0.18523167073726654,
      0.013515572063624859,
      0.09301359206438065,
      0.020835256204009056,
      -0.42316874861717224,
      0.2746310532093048,
      -0.6367192268371582,
      -0.06526912748813629,
      0.2623218297958374,
      -0.09057284146547318,
      -0.06903219223022461,
      0.32926806807518005,
      -0.16773109138011932,
      -0.3754541277885437,
      -0.04537652060389519,
      0.06833157688379288,
      -0.0516749806702137,
      0.03393648564815521,
      0.04674849659204483,
      0.19415611028671265,
      0.012974011711776257,
      0.11879995465278625,
      -0.10021265596151352,
      0.006383409257978201,
      -0.015028954483568668,
      -0.08811838179826736,
      0.14256563782691956,
      -0.12368208169937134,
      -0.07680782675743103,
      0.2684248685836792,
      -0.023867975920438766,
      0.005071620456874371,
      0.13247312605381012,
      0.11716602742671967,
      0.1929589956998825,
      -0.3315806984901428,
      -0.21728138625621796,
      0.08244892954826355,
      0.11011195182800293,
      -0.24581408500671387,
      0.19491136074066162,
      -0.3043791651725769,
      0.07471324503421783,
      -0.09346604347229004,
      0.3667925000190735,
      0.12104190140962601,
      -0.5898826122283936,
      0.12121039628982544,
      0.24038070440292358,
      -0.27105244994163513,
      -0.5731642246246338,
      -0.06952343136072159,
      0.06686990708112717,
      -0.0137805650010705,
      -0.03485821932554245,
      0.1750098168849945,
      0.07881492376327515,
      -0.1000664085149765,
      -0.051147423684597015,
      -0.02634844370186329,
      0.20412233471870422,
      0.054278839379549026,
      -0.10320546478033066,
      -0.07516776770353317,
      -0.3515634834766388,
      -0.38116830587387085,
      -0.09471500664949417,
      0.10341950505971909,
      0.016205621883273125,
      0.005972810555249453,
      0.2060994654893875,
      -0.09074340015649796,
      -0.19227564334869385,
      0.028349602594971657,
      0.18118759989738464,
      -0.056597232818603516,
      -0.19697299599647522,
      0.48010510206222534,
      0.02604604698717594,
      -0.1481340229511261,
      -0.017783204093575478,
      0.24087755382061005,
      -0.07454299181699753,
      0.02678721398115158,
      -0.13960853219032288,
      0.04771875962615013,
      0.02938319370150566,
      0.003044057870283723,
      -0.013993284665048122,
      0.17224058508872986,
      -0.04218486323952675,
      -0.03842650353908539,
      -0.3660179376602173,
      -0.03283478319644928,
      -0.09180177748203278,
      -0.26065874099731445,
      -0.0326010063290596,
      -0.20439335703849792,
      -0.15416577458381653,
      0.281178742647171,
      0.08936040848493576,
      -0.2432529777288437,
      0.24841968715190887,
      -0.2716871500015259,
      0.27375441789627075,
      -0.1110784262418747,
      0.48156049847602844,
      0.4085414707660675,
      -0.08592001348733902,
      -0.031218646094202995,
      0.03244185075163841,
      0.33597785234451294,
      -0.15686003863811493,
      0.30510663986206055,
      0.06692203134298325,
      0.19199953973293304,
      -0.21246042847633362,
      0.05156882479786873,
      0.04536056891083717,
      0.15837526321411133,
      -0.44147980213165283,
      0.34042367339134216,
      -0.04470791295170784,
      0.019863028079271317,
      0.435528427362442,
      -0.22841861844062805,
      0.2656891345977783,
      -0.08410315215587616,
      -0.07969183474779129,
      -0.03809373453259468,
      0.213131844997406,
      0.10610814392566681,
      -0.19682130217552185,
      -0.2514415681362152,
      -0.4533967971801758,
      -0.095551997423172,
      -0.15329475700855255,
      0.11418045312166214,
      -0.07264856994152069,
      0.09117498248815536,
      -0.15823501348495483,
      0.27042439579963684,
      0.053604092448949814,
      0.17583264410495758,
      -0.2918526828289032,
      -0.24714328348636627,
      0.21378254890441895,
      0.001000411924906075,
      -0.20488731563091278,
      -0.01713097281754017,
      -0.15935106575489044,
      0.06530773639678955,
      0.15303003787994385,
      0.034389253705739975,
      -0.08334184437990189,
      -0.4733904302120209,
      -0.27999791502952576,
      0.1426003873348236,
      -0.12583144009113312,
      -0.2301865816116333,
      -0.1767190396785736,
      -0.13174624741077423,
      -0.438001811504364,
      -0.49048665165901184,
      0.02256966568529606,
      0.10158291459083557,
      -0.13352055847644806,
      -0.06655877828598022,
      -0.12312876433134079,
      -0.2605009078979492,
      -0.5899537801742554
    ]
  }
}