{
  "packet_id": "interview-dhlr7zydlj8-semantics-pkt-0031",
  "source_id": "video:interview-dhlr7zydlj8",
  "source_date": "2026-01-16",
  "interactions": [
    {
      "refs": [
        "video:interview-dhlr7zydlj8@transcript:v1#seg-0241"
      ],
      "kind": "exchange",
      "summary": "The host riffs on don't, ever, fight.",
      "speaker_attribution": "Host",
      "confidence": "high"
    },
    {
      "refs": [
        "video:interview-dhlr7zydlj8@transcript:v1#seg-0242"
      ],
      "kind": "monologue",
      "summary": "Jiang talks about look, when, attacks.",
      "speaker_attribution": "Jiang",
      "confidence": "high"
    },
    {
      "refs": [
        "video:interview-dhlr7zydlj8@transcript:v1#seg-0243"
      ],
      "kind": "question",
      "summary": "The host asks about blew, face, girl's.",
      "speaker_attribution": "Host",
      "confidence": "high"
    },
    {
      "refs": [
        "video:interview-dhlr7zydlj8@transcript:v1#seg-0244"
      ],
      "kind": "answer",
      "summary": "Jiang answers about basically, can't, chain.",
      "speaker_attribution": "Jiang",
      "confidence": "high"
    },
    {
      "refs": [
        "video:interview-dhlr7zydlj8@transcript:v1#seg-0245",
        "video:interview-dhlr7zydlj8@transcript:v1#seg-0246"
      ],
      "kind": "question",
      "summary": "The host asks about right, columbus, iphone.",
      "speaker_attribution": "Host",
      "confidence": "high"
    },
    {
      "refs": [
        "video:interview-dhlr7zydlj8@transcript:v1#seg-0247"
      ],
      "kind": "unclear",
      "summary": "An uncertain side voice covers there's, building, columbus.",
      "speaker_attribution": "Show intro / side voice",
      "confidence": "low"
    },
    {
      "refs": [
        "video:interview-dhlr7zydlj8@transcript:v1#seg-0248"
      ],
      "kind": "exchange",
      "summary": "The host riffs on vows, real, that's.",
      "speaker_attribution": "Host",
      "confidence": "high"
    }
  ],
  "speaker_notes": [
    {
      "refs": [
        "video:interview-dhlr7zydlj8@transcript:v1#seg-0247"
      ],
      "note": "This voice appears to be intro sting, production chatter, or another side participant rather than the main Jiang-host exchange.",
      "suggested_speaker": "Side voice / intro audio",
      "confidence": "low"
    }
  ],
  "claims": [
    {
      "claim": "Jiang says um yeah i mean um like like look look you're talking about the hasbella the the hasbilla pager attacks right when when israel just blew up...",
      "refs": [
        "video:interview-dhlr7zydlj8@transcript:v1#seg-0242"
      ],
      "temporal_scope": "Statement made in this 2026-01-16 interview.",
      "topic_tags": [
        "look",
        "when",
        "attacks"
      ],
      "claim_type": "other",
      "confidence": "high"
    },
    {
      "claim": "Jiang says this right what it tells us is basically that israeli's control the global supply chain and you can't do that without the help of china",
      "refs": [
        "video:interview-dhlr7zydlj8@transcript:v1#seg-0244"
      ],
      "temporal_scope": "Statement made in this 2026-01-16 interview.",
      "topic_tags": [
        "basically",
        "can't",
        "chain"
      ],
      "claim_type": "other",
      "confidence": "high"
    }
  ],
  "signature_moments": [
    {
      "refs": [
        "video:interview-dhlr7zydlj8@transcript:v1#seg-0242"
      ],
      "moment": "Jiang lands the packet with a line he uses as a compressed image for the surrounding claim.",
      "source_phrase": "um yeah i mean um like like look look you're talking about the hasbella the the",
      "why_it_matters": "It preserves the packet's most memorable phrasing for later episode compression.",
      "tone": "image",
      "confidence": "high"
    }
  ],
  "glossary_terms": [],
  "chronology_notes": [],
  "uncertainty_notes": [
    {
      "refs": [
        "video:interview-dhlr7zydlj8@transcript:v1#seg-0242"
      ],
      "note": "The transcript in this span is somewhat noisy or self-correcting, so exact wording should be checked against the underlying audio if the phrase becomes public-facing."
    },
    {
      "refs": [
        "video:interview-dhlr7zydlj8@transcript:v1#seg-0245",
        "video:interview-dhlr7zydlj8@transcript:v1#seg-0246"
      ],
      "note": "The transcript in this span is somewhat noisy or self-correcting, so exact wording should be checked against the underlying audio if the phrase becomes public-facing."
    },
    {
      "refs": [
        "video:interview-dhlr7zydlj8@transcript:v1#seg-0247"
      ],
      "note": "The transcript in this span is somewhat noisy or self-correcting, so exact wording should be checked against the underlying audio if the phrase becomes public-facing."
    },
    {
      "refs": [
        "video:interview-dhlr7zydlj8@transcript:v1#seg-0248"
      ],
      "note": "The transcript in this span is somewhat noisy or self-correcting, so exact wording should be checked against the underlying audio if the phrase becomes public-facing."
    }
  ]
}
